railtracks/__init__.py
railtracks/_session.py
railtracks/py.typed
railtracks/built_nodes/__init__.py
railtracks/built_nodes/_node_builder.py
railtracks/built_nodes/concrete/__init__.py
railtracks/built_nodes/concrete/_llm_base.py
railtracks/built_nodes/concrete/_tool_call_base.py
railtracks/built_nodes/concrete/chat_tool_call_llm.py
railtracks/built_nodes/concrete/function_base.py
railtracks/built_nodes/concrete/response.py
railtracks/built_nodes/concrete/structured_llm_base.py
railtracks/built_nodes/concrete/structured_tool_call_llm_base.py
railtracks/built_nodes/concrete/terminal_llm_base.py
railtracks/built_nodes/concrete/tool_call_llm_base.py
railtracks/built_nodes/easy_usage_wrappers/__init__.py
railtracks/built_nodes/easy_usage_wrappers/agent.py
railtracks/built_nodes/easy_usage_wrappers/function.py
railtracks/built_nodes/easy_usage_wrappers/helpers/__init__.py
railtracks/built_nodes/easy_usage_wrappers/helpers/structured_llm.py
railtracks/built_nodes/easy_usage_wrappers/helpers/structured_tool_call_llm.py
railtracks/built_nodes/easy_usage_wrappers/helpers/terminal_llm.py
railtracks/built_nodes/easy_usage_wrappers/helpers/tool_call_llm.py
railtracks/context/__init__.py
railtracks/context/central.py
railtracks/context/external.py
railtracks/context/internal.py
railtracks/exceptions/__init__.py
railtracks/exceptions/_base.py
railtracks/exceptions/errors.py
railtracks/exceptions/messages/exception_messages.py
railtracks/exceptions/messages/exception_messages.yaml
railtracks/execution/__init__.py
railtracks/execution/coordinator.py
railtracks/execution/execution_strategy.py
railtracks/execution/task.py
railtracks/human_in_the_loop/__init__.py
railtracks/human_in_the_loop/human_in_the_loop.py
railtracks/human_in_the_loop/local_chat_ui.py
railtracks/integrations/__init__.py
railtracks/interaction/__init__.py
railtracks/interaction/_call.py
railtracks/interaction/batch.py
railtracks/interaction/broadcast_.py
railtracks/interaction/interactive.py
railtracks-1.115.dist-info/licenses/LICENSE
railtracks-1.115.dist-info/WHEEL
railtracks-1.115.dist-info/METADATA
railtracks-1.115.dist-info/RECORD
