Metadata-Version: 2.4
Name: railtracks
Version: 1.115
Summary: The Railtracks Framework for building resilient agentic systems in simple python
Author-email: Logan Underwood <logan@railtown.ai>, Levi Varsanyi <levi@railtown.ai>, Jaime Bueza <jaime@railtown.ai>, Amir Refaee <amir@railtown.ai>, Aryan Ballani <aryan@railtown.ai>, Tristan Brown <tristan@railtown.ai>
Requires-Python: >=3.10
Classifier: Programming Language :: Python :: 3
Classifier: Programming Language :: Python :: 3.9
Classifier: Programming Language :: Python :: 3.10
Classifier: Programming Language :: Python :: 3.11
Classifier: Programming Language :: Python :: 3.12
Classifier: License :: OSI Approved :: MIT License
Classifier: Operating System :: OS Independent
Classifier: Development Status :: 4 - Beta
Classifier: Framework :: AsyncIO
Classifier: Intended Audience :: Developers
Classifier: Intended Audience :: Science/Research
Classifier: Natural Language :: English
Classifier: Topic :: Scientific/Engineering :: Artificial Intelligence
Classifier: Topic :: Software Development :: Libraries :: Application Frameworks
Classifier: Typing :: Typed
License-File: LICENSE
Requires-Dist: colorama >= 0.4.6
Requires-Dist: litellm[proxy] >= 1.70.2
Requires-Dist: mcp >= 1.9.0
Requires-Dist: openai < 1.100.0
Requires-Dist: pydantic >= 2.5.3, <3
Requires-Dist: python-dotenv >= 1.0.0
Requires-Dist: PyYAML >= 6.0
Requires-Dist: railtracks[chat, rag, integrations] ; extra == "all"
Requires-Dist: fastapi >= 0.104.0 ; extra == "chat"
Requires-Dist: railtracks[chat] ; extra == "core"
Requires-Dist: railtracks[portkey] ; extra == "integrations"
Requires-Dist: portkey_ai >= 2.0.2 ; extra == "portkey"
Requires-Dist: litellm[proxy] >= 1.70.2 ; extra == "rag"
Requires-Dist: openai < 1.100.0 ; extra == "rag"
Project-URL: Release Notes, https://github.com/RailtownAI/railtracks/releases
Project-URL: documentation, https://railtownai.github.io/railtracks/
Project-URL: home, https://railtracks.org
Project-URL: repository, https://github.com/RailtownAI/railtracks
Provides-Extra: all
Provides-Extra: chat
Provides-Extra: core
Provides-Extra: integrations
Provides-Extra: portkey
Provides-Extra: rag
